Week 2/Assignment/alu.v
// Week 2 — 8-bit ALU
// op: 000=ADD 001=SUB 010=AND 011=OR 100=XOR 101=SHIFTL 110=SHIFTR
// Run: iverilog -o sim ../testbenches/tb_alu.v alu.v && vvp sim

module alu(
    input  [7:0]     a, b,
    input  [2:0]     op,
    output reg [7:0] result,
    output           zero,
    output reg       carry,
    output reg       overflow
);
    reg [8:0] temp;

    always @(*) begin
        result   = 8'b0;
        carry    = 1'b0;
        overflow = 1'b0;
        temp     = 9'b0;

        case (op)

            3'b000: begin
                temp     = {1'b0, a} + {1'b0, b};
                result   = temp[7:0];
                carry    = temp[8];
                overflow = (~(a[7] ^ b[7])) & (a[7] ^ result[7]);
            end

            3'b001: begin
                temp     = {1'b0, a} - {1'b0, b};
                result   = temp[7:0];
                carry    = temp[8];  // borrow indication
                overflow = (a[7] ^ b[7]) & (a[7] ^ result[7]);
            end

            3'b010: begin
                result = a & b;
            end

            3'b011: begin
                result = a | b;
            end

            3'b100: begin
                result = a ^ b;
            end

            3'b101: begin
                result = a << 1;
                carry  = a[7];
            end

            3'b110: begin
                result = a >> 1;
                carry  = a[0];
            end

            default: begin
                result   = 8'b0;
                carry    = 1'b0;
                overflow = 1'b0;
            end

        endcase
    end

    assign zero = (result == 8'b0);
endmodule

Week 2/testbenches/tb_alu.v
module tb_alu;
    reg  [7:0] a, b;
    reg  [2:0] op;
    wire [7:0] result;
    wire       zero, carry, overflow;
    integer fail = 0;

    alu uut(.a(a),.b(b),.op(op),.result(result),.zero(zero),.carry(carry),.overflow(overflow));

    task check_result;
        input [7:0] exp_result;
        input exp_zero, exp_carry;
        begin
            if (result !== exp_result) begin
                $display("FAIL op=%b a=%h b=%h: result got %h exp %h", op,a,b,result,exp_result);
                fail = fail+1;
            end
            if (zero !== exp_zero) begin
                $display("FAIL op=%b a=%h b=%h: zero got %b exp %b", op,a,b,zero,exp_zero);
                fail = fail+1;
            end
            if (carry !== exp_carry) begin
                $display("FAIL op=%b a=%h b=%h: carry got %b exp %b", op,a,b,carry,exp_carry);
                fail = fail+1;
            end
        end
    endtask

    initial begin
        $dumpfile("wave_alu.vcd"); $dumpvars(0,tb_alu);

        // ADD
        op=3'b000; a=8'd10;  b=8'd20;  #10; check_result(8'd30,  0, 0);
        op=3'b000; a=8'd0;   b=8'd0;   #10; check_result(8'd0,   1, 0);
        op=3'b000; a=8'hFF;  b=8'h01;  #10; check_result(8'h00,  1, 1); // carry

        // SUB
        op=3'b001; a=8'd30;  b=8'd10;  #10; check_result(8'd20,  0, 0);
        op=3'b001; a=8'd10;  b=8'd10;  #10; check_result(8'd0,   1, 0);

        // AND
        op=3'b010; a=8'hFF;  b=8'h0F;  #10; check_result(8'h0F,  0, 0);

        // OR
        op=3'b011; a=8'hF0;  b=8'h0F;  #10; check_result(8'hFF,  0, 0);

        // XOR
        op=3'b100; a=8'hFF;  b=8'hFF;  #10; check_result(8'h00,  1, 0);

        // SHIFTL
        op=3'b101; a=8'b00000001; b=8'b0; #10; check_result(8'b00000010, 0, 0);
        op=3'b101; a=8'b10000000; b=8'b0; #10; check_result(8'b00000000, 1, 1);

        // SHIFTR
        op=3'b110; a=8'b10000000; b=8'b0; #10; check_result(8'b01000000, 0, 0);

        if(fail==0) $display("PASS — all ALU checks passed.");
        else        $display("FAIL — %0d check(s) failed.", fail);
        $finish;
    end
endmodule

Week 2/Assignment/wave_alu.vcd
$date
	Sun May 31 18:47:42 2026
$end
$version
	Icarus Verilog
$end
$timescale
	1s
$end
$scope module tb_alu $end
$var wire 1 ! zero $end
$var wire 8 " result [7:0] $end
$var wire 1 # overflow $end
$var wire 1 $ carry $end
$var reg 8 % a [7:0] $end
$var reg 8 & b [7:0] $end
$var reg 3 ' op [2:0] $end
$var integer 32 ( fail [31:0] $end
$scope module uut $end
$var wire 8 ) a [7:0] $end
$var wire 8 * b [7:0] $end
$var wire 3 + op [2:0] $end
$var wire 1 ! zero $end
$var reg 1 $ carry $end
$var reg 1 # overflow $end
$var reg 8 , result [7:0] $end
$var reg 9 - temp [8:0] $end
$upscope $end
$scope task check_result $end
$var reg 1 . exp_carry $end
$var reg 8 / exp_result [7:0] $end
$var reg 1 0 exp_zero $end
$upscope $end
$upscope $end
$enddefinitions $end
$comment Show the parameter values. $end
$dumpall
$end
#0
$dumpvars
x0
bx /
x.
b11110 -
b11110 ,
b0 +
b10100 *
b1010 )
b0 (
b0 '
b10100 &
b1010 %
0$
0#
b11110 "
0!
$end
#10
b0 -
1!
b0 "
b0 ,
b0 &
b0 *
b0 %
b0 )
0.
00
b11110 /
#20
1$
b100000000 -
b1 &
b1 *
b11111111 %
b11111111 )
10
b0 /
#30
0!
b10100 "
b10100 ,
b10100 -
0$
b1010 &
b1010 *
b11110 %
b11110 )
b1 '
b1 +
1.
#40
b0 -
1!
b0 "
b0 ,
b1010 %
b1010 )
0.
00
b10100 /
#50
0!
b1111 "
b1111 ,
b1111 &
b1111 *
b11111111 %
b11111111 )
b10 '
b10 +
10
b0 /
#60
0!
b11111111 "
b11111111 ,
b11110000 %
b11110000 )
b11 '
b11 +
00
b1111 /
#70
1!
b0 "
b0 ,
b11111111 &
b11111111 *
b11111111 %
b11111111 )
b100 '
b100 +
b11111111 /
#80
0!
b10 "
b10 ,
b0 &
b0 *
b1 %
b1 )
b101 '
b101 +
10
b0 /
#90
1$
1!
b0 "
b0 ,
b10000000 %
b10000000 )
00
b10 /
#100
0!
b1000000 "
b1000000 ,
0$
b110 '
b110 +
1.
10
b0 /
#110
0.
00
b1000000 /
